LICENSE
README.md
sqlean/__init__.py
sqlean/bigquery_functions.lark
sqlean/custom_classes.py
sqlean/definitions.py
sqlean/grammar/comment.lark
sqlean/grammar/jinja.lark
sqlean/grammar/literal.lark
sqlean/grammar/reserved_words.lark
sqlean/grammar/sql.lark
sqlean/main.py
sqlean/settings.py
sqlean/sql_parser.py
sqlean/sql_styler.py
sqlean/stats.py
sqlean-0.0.3.dist-info/entry_points.txt
sqlean-0.0.3.dist-info/LICENSE
sqlean-0.0.3.dist-info/WHEEL
sqlean-0.0.3.dist-info/METADATA
sqlean-0.0.3.dist-info/RECORD
