Metadata-Version: 2.1
Name: sqlean
Version: 0.0.3
Summary: Clean your SQL queries
Home-page: https://github.com/oliverxchen/sqlean
License: MIT
Keywords: sql,linter
Author: Oliver Chen
Author-email: oliverxchen@gmail.com
Requires-Python: >=3.7,<4.0
Classifier: License :: OSI Approved :: MIT License
Classifier: Programming Language :: Python :: 3
Classifier: Programming Language :: Python :: 3.10
Classifier: Programming Language :: Python :: 3.7
Classifier: Programming Language :: Python :: 3.8
Classifier: Programming Language :: Python :: 3.9
Requires-Dist: black (>=21.4b)
Requires-Dist: lark (>=1.1.0)
Requires-Dist: pydantic (>=1.8.2)
Requires-Dist: rich (>=10.0)
Requires-Dist: tomli (>=1.0.0)
Requires-Dist: typer (>=0.4.0)
Project-URL: Repository, https://github.com/oliverxchen/sqlean
